Workbook

Sheet Funding_info
A1: Funding_info
A2: One row per field. The dashboard reads column B. Fill the yellow cells; grey cells are formulas over the Budget tab - do not edit them.
A4: Funding source | B4: SPY_26_EXAMPLE | C4: Must match the file name AND the Xero 'Funding source' tracking value
A5: Project | B5: Spyfish Aotearoa | C5: Default project for lines with a blank Project cell
A6: Funder | B6: Example Funder Trust | C6: The organisation
A7: Income recognition | C7: as spent for a grant paid upfront and released as it is spent; blank or as invoiced otherwise
A8: Funding start | B8: 46204 | C8: First day of the grant period
A9: Funding end | B9: 46568 | C9: Last day. Lets the dashboard flag spend after a grant ends
A10: Contribution policy | B10: percent_of_income:40 | C10: none | percent_of_income:<n> | per_line
A11: Amount secured | B11: 0 | C11: GST exclusive. 0 while the bid is proposed
A12: Decision date | B12: 46188 | C12: When the funder decides. Blank once secured
A13: Probability | B13: 60% | C13: 0 to 100, proposed only: the chance this ask is won
A14: Exclusivity group | C14: A label shared by competing applications for the same work
A15: Owner | B15: owner@example.org | C15: Health findings for this sheet are addressed here
A16: Last reviewed | B16: 46245 | C16: Date last checked against reality
A17: Link | B17: https://drive.google.com/drive/folders/EXAMPLE
A18: Notes | C18: Free text. Never put a number here that anything else needs
A19: Amount requested | B19: =SUM(Budget!E:E) | C19: Derived: total Income on the Budget tab
A21: Derived from the Budget tab - do not edit
A22: Total cost | B22: =SUM(Budget!D:D) | C22: Sum of the Cost column
A23: Total income | B23: =SUM(Budget!E:E) | C23: Sum of the Income column
A24: Total contribution | B24: =SUM(Budget!F:F) | C24: Income minus Cost, per line
A25: Contribution as % of income | B25: =IFERROR(B24/B23,0) | C25: Should match the Contribution policy above

Sheet Budget
A1: Budget - the live baseline the dashboard reads. One row per milestone, or several rows sharing one Xero Inventory Item. Do NOT add a totals row: it would be parsed as a budget line. Totals live on Funding_info.
A2: Description | B2: Start | C2: End | D2: Cost | E2: Income | F2: Contribution | G2: Milestone | H2: Xero Inventory Item | I2: Project | J2: Comments
A3: Data Scientist | B3: 46204 | C3: 46387 | D3: 12000 | E3: 20000 | F3: =E3-D3 | G3: Baseline model assessment and data ingestion | H3: SPY_26_EXAMPLE_001 - Baseline model assessment | J3: Illustrative figures only - replace with your own
A4: Project Manager | B4: 46204 | C4: 46387 | D4: 3000 | E4: 5000 | F4: =E4-D4 | G4: Baseline model assessment and data ingestion | H4: SPY_26_EXAMPLE_001 - Baseline model assessment | J4: Second row on the same milestone, split by role
A5: Data Scientist | B5: 46388 | C5: 46568 | D5: 12000 | E5: 20000 | F5: =E5-D5 | G5: Final validation and co-authored manuscript | H5: SPY_26_EXAMPLE_002 - Final validation and manuscript | J5: Illustrative figures only
A6: Project Manager | B6: 46388 | C6: 46568 | D6: 3000 | E6: 5000 | F6: =E6-D6 | G6: Final validation and co-authored manuscript | H6: SPY_26_EXAMPLE_002 - Final validation and manuscript | I6: General | J6: Project column sends this line to General

Sheet Forecast
A1: Forecast - OPTIONAL per-quarter overrides. A quarter with no entry falls back to the budget baseline, so an empty tab is fine. Column headers must read exactly 'MMM-MMM YY Forecast'. Rows must start with the Xero Inventory Item code.
A3: Revenue | B3: =IF(Funding_info!$B$8="","",TEXT(EOMONTH(EOMONTH(Funding_info!$B$8, -MOD(MONTH(Funding_info!$B$8)-1, 3) - 1), 1), "mmm") & "-" & TEXT(EOMONTH(EOMONTH(Funding_info!$B$8, -MOD(MONTH(Funding_info!$B$8)-1, 3) - 1), 3), "mmm yy") & " Forecast") | C3: =IF(Funding_info!$B$8="","",TEXT(EOMONTH(EOMONTH(Funding_info!$B$8, -MOD(MONTH(Funding_info!$B$8)-1, 3) - 1), 4), "mmm") & "-" & TEXT(EOMONTH(EOMONTH(Funding_info!$B$8, -MOD(MONTH(Funding_info!$B$8)-1, 3) - 1), 6), "mmm yy") & " Forecast") | D3: =IF(Funding_info!$B$8="","",TEXT(EOMONTH(EOMONTH(Funding_info!$B$8, -MOD(MONTH(Funding_info!$B$8)-1, 3) - 1), 7), "mmm") & "-" & TEXT(EOMONTH(EOMONTH(Funding_info!$B$8, -MOD(MONTH(Funding_info!$B$8)-1, 3) - 1), 9), "mmm yy") & " Forecast") | E3: =IF(Funding_info!$B$8="","",TEXT(EOMONTH(EOMONTH(Funding_info!$B$8, -MOD(MONTH(Funding_info!$B$8)-1, 3) - 1), 10), "mmm") & "-" & TEXT(EOMONTH(EOMONTH(Funding_info!$B$8, -MOD(MONTH(Funding_info!$B$8)-1, 3) - 1), 12), "mmm yy") & " Forecast") | F3: Comments
A4: SPY_26_EXAMPLE_001 - Baseline model assessment | B4: 25000 | F4: On signing of the agreement
A5: SPY_26_EXAMPLE_002 - Final validation and manuscript | D5: 25000 | F5: On completion of the research
A6: Total | B6: =SUM(B4:B5) | C6: =SUM(C4:C5) | D6: =SUM(D4:D5) | E6: =SUM(E4:E5)
A8: Expenses | B8: =IF(Funding_info!$B$8="","",TEXT(EOMONTH(EOMONTH(Funding_info!$B$8, -MOD(MONTH(Funding_info!$B$8)-1, 3) - 1), 1), "mmm") & "-" & TEXT(EOMONTH(EOMONTH(Funding_info!$B$8, -MOD(MONTH(Funding_info!$B$8)-1, 3) - 1), 3), "mmm yy") & " Forecast") | C8: =IF(Funding_info!$B$8="","",TEXT(EOMONTH(EOMONTH(Funding_info!$B$8, -MOD(MONTH(Funding_info!$B$8)-1, 3) - 1), 4), "mmm") & "-" & TEXT(EOMONTH(EOMONTH(Funding_info!$B$8, -MOD(MONTH(Funding_info!$B$8)-1, 3) - 1), 6), "mmm yy") & " Forecast") | D8: =IF(Funding_info!$B$8="","",TEXT(EOMONTH(EOMONTH(Funding_info!$B$8, -MOD(MONTH(Funding_info!$B$8)-1, 3) - 1), 7), "mmm") & "-" & TEXT(EOMONTH(EOMONTH(Funding_info!$B$8, -MOD(MONTH(Funding_info!$B$8)-1, 3) - 1), 9), "mmm yy") & " Forecast") | E8: =IF(Funding_info!$B$8="","",TEXT(EOMONTH(EOMONTH(Funding_info!$B$8, -MOD(MONTH(Funding_info!$B$8)-1, 3) - 1), 10), "mmm") & "-" & TEXT(EOMONTH(EOMONTH(Funding_info!$B$8, -MOD(MONTH(Funding_info!$B$8)-1, 3) - 1), 12), "mmm yy") & " Forecast") | F8: Comments
A9: SPY_26_EXAMPLE_001 - Baseline model assessment | B9: 15000 | F9: Both roles, to December
A10: SPY_26_EXAMPLE_002 - Final validation and manuscript | D10: 15000 | F10: Both roles, second half
A11: Total | B11: =SUM(B9:B10) | C11: =SUM(C9:C10) | D11: =SUM(D9:D10) | E11: =SUM(E9:E10)
A13: Funding Source Details
A14: Nothing below this row is read. Keep working notes here.

Sheet Submitted_budget
A1: Submitted_budget - a frozen copy of what the funder was actually given. Not read by the dashboard. Never edit after submission; re-budgets go on the Budget tab.
A2: Milestone | B2: Start | C2: End | D2: Amount (GST exclusive)
A3: Baseline model assessment and data ingestion | B3: 46204 | C3: 46387 | D3: 25000
A4: Final validation and co-authored manuscript | B4: 46388 | C4: 46568 | D4: 25000
A5: Total expenses (GST exclusive) | D5: =SUM(D3:D4)
